django_vite/__init__.py
django_vite/apps.py
django_vite/core/__init__.py
django_vite/core/asset_loader.py
django_vite/core/exceptions.py
django_vite/core/tag_generator.py
django_vite/templatetags/__init__.py
django_vite/templatetags/django_vite.py
django_vite-3.0.5.dist-info/LICENSE
django_vite-3.0.5.dist-info/METADATA
django_vite-3.0.5.dist-info/WHEEL
django_vite-3.0.5.dist-info/top_level.txt
django_vite-3.0.5.dist-info/RECORD
