Metadata-Version: 2.1
Name: django-vite
Version: 3.0.5
Summary: Integration of Vite in a Django project.
Home-page: https://github.com/MrBin99/django-vite
Author: MrBin99
License: Apache License, Version 2.0
Classifier: License :: OSI Approved :: Apache Software License
Classifier: Framework :: Django
Classifier: Framework :: Django :: 3.2
Classifier: Framework :: Django :: 4.0
Classifier: Framework :: Django :: 4.1
Classifier: Framework :: Django :: 4.2
Classifier: Programming Language :: Python
Classifier: Programming Language :: Python :: 3.8
Classifier: Programming Language :: Python :: 3.9
Classifier: Programming Language :: Python :: 3.10
Classifier: Programming Language :: Python :: 3.11
Classifier: Programming Language :: Python :: 3.12
Requires: Django (>=3.2)
License-File: LICENSE
Requires-Dist: Django>=3.2
Provides-Extra: dev
Requires-Dist: black; extra == "dev"
